jia_encryption/__init__.py
jia_encryption/__version__.py
jia_encryption/build_and_publish.py
jia_encryption/cli.py
jia_encryption/config.py
jia_encryption/encryption_api.py
jia_encryption/encryption_core.py
jia_encryption/session_manager.py
jia_encryption/setup.py
jia_encryption/utils.py
jia_encryption/tests/__init__.py
jia_encryption/tests/test_encryption_api.py
jia_encryption/tests/test_encryption_core.py
jia_encryption/tests/test_utils.py
jia512-1.0.1.dist-info/LICENSE
jia512-1.0.1.dist-info/METADATA
jia512-1.0.1.dist-info/WHEEL
jia512-1.0.1.dist-info/entry_points.txt
jia512-1.0.1.dist-info/top_level.txt
jia512-1.0.1.dist-info/RECORD
