Metadata-Version: 2.1
Name: jia512
Version: 1.0.1
Summary: 轻量级加密解密框架，提供RSA-AES混合加密功能
Home-page: https://github.com/xiayunlong/jia
Author: 夏云龙
Author-email: 夏云龙 <xiayunlong@example.com>
Maintainer-email: 夏云龙 <xiayunlong@example.com>
License: MIT
Project-URL: Homepage, https://github.com/xiayunlong/jia
Project-URL: Documentation, https://github.com/xiayunlong/jia/blob/main/README.md
Project-URL: Repository, https://github.com/xiayunlong/jia
Project-URL: Bug Tracker, https://github.com/xiayunlong/jia/issues
Keywords: encryption,cryptography,rsa,aes,hmac,security,async
Classifier: Development Status :: 4 - Beta
Classifier: Intended Audience :: Developers
Classifier: License :: OSI Approved :: MIT License
Classifier: Operating System :: OS Independent
Classifier: Programming Language :: Python :: 3
Classifier: Programming Language :: Python :: 3.7
Classifier: Programming Language :: Python :: 3.8
Classifier: Programming Language :: Python :: 3.9
Classifier: Programming Language :: Python :: 3.10
Classifier: Programming Language :: Python :: 3.11
Classifier: Programming Language :: Python :: 3.12
Classifier: Topic :: Security :: Cryptography
Classifier: Topic :: Software Development :: Libraries :: Python Modules
Classifier: Topic :: System :: Distributed Computing
Requires-Python: >=3.7
License-File: LICENSE
Requires-Dist: cryptography>=3.4.8
Provides-Extra: dev
Requires-Dist: pytest>=6.0.0; extra == "dev"
Requires-Dist: pytest-asyncio>=0.18.0; extra == "dev"
Requires-Dist: black>=21.0.0; extra == "dev"
Requires-Dist: flake8>=3.8.0; extra == "dev"
Requires-Dist: mypy>=0.800; extra == "dev"
Requires-Dist: twine>=3.4.0; extra == "dev"
Requires-Dist: wheel>=0.37.0; extra == "dev"
Provides-Extra: docs
Requires-Dist: sphinx>=4.0.0; extra == "docs"
Requires-Dist: sphinx-rtd-theme>=1.0.0; extra == "docs"
Provides-Extra: redis
Requires-Dist: redis>=4.0.0; extra == "redis"
